flake8_ban_utcnow.py
flake8_ban_utcnow_36-0.2.0.dist-info/LICENCE
flake8_ban_utcnow_36-0.2.0.dist-info/METADATA
flake8_ban_utcnow_36-0.2.0.dist-info/WHEEL
flake8_ban_utcnow_36-0.2.0.dist-info/entry_points.txt
flake8_ban_utcnow_36-0.2.0.dist-info/top_level.txt
flake8_ban_utcnow_36-0.2.0.dist-info/RECORD
