Metadata-Version: 2.1
Name: flake8-ban-utcnow-36
Version: 0.2.0
Summary: flake8 plugin which bans the usage of datetime.datetime.utcnow. Forked to support 3.6.
Home-page: https://github.com/LiamClarkeNZ/flake8-ban-utcnow-36
Author: Jonas Kittner
Author-email: jkittner@users.noreply.github.com
Maintainer: Liam Clarke-Hutchinson
License: MIT
Platform: UNKNOWN
Classifier: License :: OSI Approved :: MIT License
Classifier: Programming Language :: Python :: 3
Classifier: Programming Language :: Python :: 3 :: Only
Classifier: Programming Language :: Python :: Implementation :: CPython
Requires-Python: ~=3.6
License-File: LICENCE
Requires-Dist: flake8 (<=3.7.7)
